gauto_profiler/__init__.py
gauto_profiler/config.py
gauto_profiler/profiler.py
gauto_profiler/core/__init__.py
gauto_profiler/core/base.py
gauto_profiler/core/chart.py
gauto_profiler/core/cpu.py
gauto_profiler/core/fps.py
gauto_profiler/core/mem.py
gauto_profiler/utils/__init__.py
gauto_profiler/utils/adb_tool.py
gauto_profiler-0.1.2.dist-info/METADATA
gauto_profiler-0.1.2.dist-info/WHEEL
gauto_profiler-0.1.2.dist-info/top_level.txt
gauto_profiler-0.1.2.dist-info/RECORD
