Metadata-Version: 2.1
Name: gauto-profiler
Version: 0.1.2
Summary: A tool for game automation on android platform
Home-page: https://github.com/qintianchen/AndroidGameProfiler.git
Author: qintianchen
Author-email: 1365265750@qq.com
License: MIT Licence
Platform: UNKNOWN
Requires-Python: >=3.4
